PyChakra/__init__.py
PyChakra/libs/linux/libChakraCore.so
PyChakra/libs/osx/libChakraCore.dylib
PyChakra/libs/windows/x64/ChakraCore.dll
PyChakra/libs/windows/x86/ChakraCore.dll
PyChakra-2.1.3.dist-info/LICENSE
PyChakra-2.1.3.dist-info/METADATA
PyChakra-2.1.3.dist-info/WHEEL
PyChakra-2.1.3.dist-info/top_level.txt
PyChakra-2.1.3.dist-info/RECORD
